{
  "teams": [
    {
      "id": 1,
      "image": "/img/team/1.svg",
      "title": "Stephanie Lawrence",
      "sub": "CEO, Colabrio Media"
    },
    {
      "id": 2,
      "image": "/img/team/2.svg",
      "title": "Alex Regelman",
      "sub": "CEO, Colabrio Media"
    },
    {
      "id": 3,
      "image": "/img/team/3.svg",
      "title": "Stacey Stamper",
      "sub": "CEO, Colabrio Media"
    },
    {
      "id": 4,
      "image": "/img/team/4.svg",
      "title": "Stephanie Lawrence",
      "sub": "CEO, Colabrio Media"
    }
  ],
  "skills": [
    {
      "id": 1,
      "text": "Decentralized Finance Applications",
      "Paragraph": "The exchanges and marketplaces will allow anyone around the world to buy, trade, invest, and lend - even without a bank account.",
      "value": "90%"
    },
    {
      "id": 2,
      "text": "Resilient, autonomous organizations",
      "Paragraph": " Empower the community to organize and allocate resources to its members. Impactful products and services on different markets.",
      "value": "80%"
    }
  ]
}
